aiolxd/__init__.py
aiolxd/api/__init__.py
aiolxd/api/abc.py
aiolxd/api/instance.py
aiolxd/entities/__init__.py
aiolxd/entities/abc.py
aiolxd/entities/instance.py
aiolxd/entities/response.py
aiolxd/entities/status.py
aiolxd/exceptions.py
aiolxd/lxd.py
aiolxd/transport.py
aiolxd/utils.py
aiolxd-0.1.1.dist-info/LICENSE
aiolxd-0.1.1.dist-info/WHEEL
aiolxd-0.1.1.dist-info/METADATA
aiolxd-0.1.1.dist-info/RECORD
