Metadata-Version: 2.1
Name: aiolxd
Version: 0.1.1
Summary: AsyncIO LXD API for Python 3
Home-page: https://github.com/cofob/aiolxd
Author: Egor Ternovoy
Author-email: cofob@riseup.net
Requires-Python: >=3.8,<4
Classifier: Programming Language :: Python :: 3
Classifier: Programming Language :: Python :: 3.8
Classifier: Programming Language :: Python :: 3.9
Classifier: Programming Language :: Python :: 3.10
Classifier: Programming Language :: Python :: 3.11
Requires-Dist: aiohttp (>=3.8,<4.0)
Requires-Dist: pydantic (>=1.10,<2.0)
Project-URL: Repository, https://github.com/cofob/aiolxd
